euph/__main__.py
euph/plusdata/__init__.py
euph/plusdata/licenses.py
euph/plusdata/texts.py
euph-1.1.3.dist-info/LICENSE
euph-1.1.3.dist-info/METADATA
euph-1.1.3.dist-info/WHEEL
euph-1.1.3.dist-info/top_level.txt
euph-1.1.3.dist-info/RECORD
