Metadata-Version: 2.1
Name: euph
Version: 1.1.3
Summary: Module for fast initialization of packages
Author-email: Markada <markada.py@gmail.com>
License: MIT License
Keywords: markada,euph,euphoria,pack
Classifier: Development Status :: 5 - Production/Stable
Classifier: Environment :: Console
Classifier: Intended Audience :: Developers
Classifier: License :: OSI Approved :: MIT License
Classifier: Natural Language :: English
Classifier: Programming Language :: Python :: 3
Requires-Python: >=3.8
License-File: LICENSE
Requires-Dist: colorama
